{
  "name": "vcomp14",
  "version": "14.44.35208",
  "build": "h818238b_31",
  "build_number": 31,
  "channel": "https://conda.anaconda.org/conda-forge/noarch",
  "subdir": "win-64",
  "fn": "vcomp14-14.44.35208-h818238b_31.conda",
  "md5": "a6b1d5c1fc3cb89f88f7179ee6a9afe3",
  "url": "https://conda.anaconda.org/conda-forge/win-64/vcomp14-14.44.35208-h818238b_31.conda",
  "sha256": "67b317b64f47635415776718d25170a9a6f9a1218c0f5a6202bfd687e07b6ea4",
  "depends": [
    "ucrt >=10.0.20348.0"
  ],
  "constrains": [
    "vs2015_runtime 14.44.35208.* *_31"
  ],
  "license": "LicenseRef-MicrosoftVisualCpp2015-2022Runtime",
  "timestamp": 1753739198000,
  "size": 113963,
  "requested_spec": "None",
  "package_tarball_full_path": "C:\\Users\\User\\miniconda3\\pkgs\\vcomp14-14.44.35208-h818238b_31.conda",
  "extracted_package_dir": "C:\\Users\\User\\miniconda3\\pkgs\\vcomp14-14.44.35208-h818238b_31",
  "files": [
    "Library/bin/vcomp140.dll",
    "vcomp140.dll"
  ],
  "paths_data": {
    "paths_version": 1,
    "paths": [
      {
        "_path": "Library/bin/vcomp140.dll",
        "no_link": true,
        "path_type": "hardlink",
        "sha256": "e7e50211906ab1c6226a3133fda8d8c8e35a23a8b6c6133c9606601604680b85",
        "size_in_bytes": 193184,
        "sha256_in_prefix": "e7e50211906ab1c6226a3133fda8d8c8e35a23a8b6c6133c9606601604680b85"
      },
      {
        "_path": "vcomp140.dll",
        "path_type": "hardlink",
        "sha256": "e7e50211906ab1c6226a3133fda8d8c8e35a23a8b6c6133c9606601604680b85",
        "size_in_bytes": 193184,
        "sha256_in_prefix": "e7e50211906ab1c6226a3133fda8d8c8e35a23a8b6c6133c9606601604680b85"
      }
    ]
  },
  "link": {
    "source": "C:\\Users\\User\\miniconda3\\pkgs\\vcomp14-14.44.35208-h818238b_31",
    "type": 1
  }
}